Metadata-Version: 2.1
Name: linux-mouse-record
Version: 0.1
Summary: Simple CLI to record and replay mouse events
Author: Read with ai
Author-email: talwrii@gmail.com
License: MIT
Keywords: mouse,LINUX,record
